{
    "list": [
        {
            "Description": null,
            "bulk": null,
            "crud": "1",
            "deleteById": null,
            "fullpath": null,
            "getById": null,
            "idpath": null,
            "paramDef": null,
            "path": "equipment",
            "post": null,
            "putById": null,
            "respDef": null,
            "tag": "Equipment"
        },
        {
            "Description": null,
            "bulk": null,
            "crud": "1",
            "deleteById": null,
            "fullpath": null,
            "getById": null,
            "idpath": null,
            "paramDef": null,
            "path": "equipmentTypes",
            "post": null,
            "putById": null,
            "respDef": null,
            "tag": "EquipmentType"
        },
        {
            "Description": null,
            "bulk": null,
            "crud": "1",
            "deleteById": null,
            "fullpath": null,
            "getById": null,
            "idpath": null,
            "paramDef": null,
            "path": "equipmentAttachmentTypes",
            "post": null,
            "putById": null,
            "respDef": null,
            "tag": "EquipmentAttachmentType"
        },
        {
            "Description": null,
            "bulk": null,
            "crud": "1",
            "deleteById": null,
            "fullpath": null,
            "getById": null,
            "idpath": null,
            "paramDef": null,
            "path": "owners",
            "post": null,
            "putById": null,
            "respDef": null,
            "tag": "Owner"
        },
        {
            "Description": null,
            "bulk": null,
            "crud": "1",
            "deleteById": null,
            "fullpath": null,
            "getById": null,
            "idpath": null,
            "paramDef": null,
            "path": "projects",
            "post": null,
            "putById": null,
            "respDef": null,
            "tag": "Project"
        },
        {
            "Description": null,
            "bulk": null,
            "crud": "1",
            "deleteById": null,
            "fullpath": null,
            "getById": null,
            "idpath": null,
            "paramDef": null,
            "path": "groups",
            "post": null,
            "putById": null,
            "respDef": null,
            "tag": "Group"
        },
        {
            "Description": null,
            "bulk": null,
            "crud": "1",
            "deleteById": null,
            "fullpath": null,
            "getById": null,
            "idpath": null,
            "paramDef": "PermissionViewModel",
            "path": "permissions",
            "post": null,
            "putById": null,
            "respDef": null,
            "tag": "Permission"
        },
        {
            "Description": null,
            "bulk": "1",
            "crud": null,
            "deleteById": null,
            "fullpath": null,
            "getById": null,
            "idpath": null,
            "paramDef": "Permission",
            "path": "permissions",
            "post": null,
            "putById": null,
            "respDef": null,
            "tag": "Permission"
        },
        {
            "Description": null,
            "bulk": null,
            "crud": "1",
            "deleteById": null,
            "fullpath": null,
            "getById": null,
            "idpath": null,
            "paramDef": "RoleViewModel",
            "path": "roles",
            "post": null,
            "putById": null,
            "respDef": null,
            "tag": "Role"
        },
        {
            "Description": null,
            "bulk": "1",
            "crud": null,
            "deleteById": null,
            "fullpath": null,
            "getById": null,
            "idpath": null,
            "paramDef": "Role",
            "path": "roles",
            "post": null,
            "putById": null,
            "respDef": null,
            "tag": "Role"
        },
        {
            "Description": null,
            "bulk": "1",
            "crud": null,
            "deleteById": null,
            "fullpath": null,
            "getById": null,
            "idpath": null,
            "paramDef": "RolePermission",
            "path": "rolepermissions",
            "post": null,
            "putById": null,
            "respDef": null,
            "tag": "Role"
        },
        {
            "Description": null,
            "bulk": null,
            "crud": "1",
            "deleteById": null,
            "fullpath": null,
            "getById": null,
            "idpath": null,
            "paramDef": "UserViewModel",
            "path": "users",
            "post": null,
            "putById": null,
            "respDef": null,
            "tag": "User"
        },
        {
            "Description": null,
            "bulk": "1",
            "crud": null,
            "deleteById": null,
            "fullpath": null,
            "getById": null,
            "idpath": null,
            "paramDef": "User",
            "path": "users",
            "post": null,
            "putById": null,
            "respDef": null,
            "tag": "User"
        },
        {
            "Description": null,
            "bulk": "1",
            "crud": null,
            "deleteById": null,
            "fullpath": null,
            "getById": null,
            "idpath": null,
            "paramDef": "GroupMembership",
            "path": "usergroups",
            "post": null,
            "putById": null,
            "respDef": null,
            "tag": "User"
        },
        {
            "Description": null,
            "bulk": "1",
            "crud": null,
            "deleteById": null,
            "fullpath": null,
            "getById": null,
            "idpath": null,
            "paramDef": "UserRole",
            "path": "userroles",
            "post": null,
            "putById": null,
            "respDef": null,
            "tag": "User"
        },
        {
            "Description": null,
            "bulk": null,
            "crud": "1",
            "deleteById": null,
            "fullpath": null,
            "getById": null,
            "idpath": null,
            "paramDef": null,
            "path": "regions",
            "post": null,
            "putById": null,
            "respDef": null,
            "tag": "Region"
        },
        {
            "Description": null,
            "bulk": null,
            "crud": "1",
            "deleteById": null,
            "fullpath": null,
            "getById": null,
            "idpath": null,
            "paramDef": null,
            "path": "districts",
            "post": null,
            "putById": null,
            "respDef": null,
            "tag": "District"
        },
        {
            "Description": null,
            "bulk": null,
            "crud": "1",
            "deleteById": null,
            "fullpath": null,
            "getById": null,
            "idpath": null,
            "paramDef": null,
            "path": "serviceareas",
            "post": null,
            "putById": null,
            "respDef": null,
            "tag": "ServiceArea"
        },
        {
            "Description": null,
            "bulk": null,
            "crud": "1",
            "deleteById": null,
            "fullpath": null,
            "getById": null,
            "idpath": null,
            "paramDef": null,
            "path": "cities",
            "post": null,
            "putById": null,
            "respDef": null,
            "tag": "City"
        },
        {
            "Description": null,
            "bulk": null,
            "crud": "1",
            "deleteById": null,
            "fullpath": null,
            "getById": null,
            "idpath": null,
            "paramDef": null,
            "path": "localAreas",
            "post": null,
            "putById": null,
            "respDef": null,
            "tag": "LocalArea"
        },
        {
            "Description": null,
            "bulk": null,
            "crud": "1",
            "deleteById": null,
            "fullpath": null,
            "getById": null,
            "idpath": null,
            "paramDef": "Contact",
            "path": "contacts",
            "post": null,
            "putById": null,
            "respDef": null,
            "tag": "Contact"
        },
        {
            "Description": null,
            "bulk": "1",
            "crud": null,
            "deleteById": null,
            "fullpath": null,
            "getById": null,
            "idpath": null,
            "paramDef": "Contact",
            "path": "contacts",
            "post": null,
            "putById": null,
            "respDef": null,
            "tag": "Contact"
        },
        {
            "Description": null,
            "bulk": null,
            "crud": "1",
            "deleteById": null,
            "fullpath": null,
            "getById": null,
            "idpath": null,
            "paramDef": "DumpTruck",
            "path": "dumptrucks",
            "post": null,
            "putById": null,
            "respDef": null,
            "tag": "DumpTruck"
        },
        {
            "Description": null,
            "bulk": "1",
            "crud": null,
            "deleteById": null,
            "fullpath": null,
            "getById": null,
            "idpath": null,
            "paramDef": "DumpTruck",
            "path": "dumptrucks",
            "post": null,
            "putById": null,
            "respDef": null,
            "tag": "DumpTruck"
        },
        {
            "Description": null,
            "bulk": null,
            "crud": "1",
            "deleteById": null,
            "fullpath": null,
            "getById": null,
            "idpath": null,
            "paramDef": "Note",
            "path": "notes",
            "post": null,
            "putById": null,
            "respDef": null,
            "tag": "Note"
        },
        {
            "Description": null,
            "bulk": "1",
            "crud": null,
            "deleteById": null,
            "fullpath": null,
            "getById": null,
            "idpath": null,
            "paramDef": "Note",
            "path": "notes",
            "post": null,
            "putById": null,
            "respDef": null,
            "tag": "Note"
        },
        {
            "Description": null,
            "bulk": null,
            "crud": "1",
            "deleteById": null,
            "fullpath": null,
            "getById": null,
            "idpath": null,
            "paramDef": "Attachment",
            "path": "attachment",
            "post": null,
            "putById": null,
            "respDef": null,
            "tag": "Attachment"
        },
        {
            "Description": null,
            "bulk": "1",
            "crud": null,
            "deleteById": null,
            "fullpath": null,
            "getById": null,
            "idpath": null,
            "paramDef": "Attachment",
            "path": "attachment",
            "post": null,
            "putById": null,
            "respDef": null,
            "tag": "Attachment"
        },
        {
            "Description": null,
            "bulk": null,
            "crud": "1",
            "deleteById": null,
            "fullpath": null,
            "getById": null,
            "idpath": null,
            "paramDef": "ContactPhone",
            "path": "contactphones",
            "post": null,
            "putById": null,
            "respDef": null,
            "tag": "ContactPhone"
        },
        {
            "Description": null,
            "bulk": "1",
            "crud": null,
            "deleteById": null,
            "fullpath": null,
            "getById": null,
            "idpath": null,
            "paramDef": "ContactPhone",
            "path": "contactphones",
            "post": null,
            "putById": null,
            "respDef": null,
            "tag": "ContactPhone"
        },
        {
            "Description": null,
            "bulk": null,
            "crud": "1",
            "deleteById": null,
            "fullpath": null,
            "getById": null,
            "idpath": null,
            "paramDef": "ContactAddress",
            "path": "contactaddresses",
            "post": null,
            "putById": null,
            "respDef": null,
            "tag": "ContactAddress"
        },
        {
            "Description": null,
            "bulk": "1",
            "crud": null,
            "deleteById": null,
            "fullpath": null,
            "getById": null,
            "idpath": null,
            "paramDef": "ContactAddress",
            "path": "contactaddresses",
            "post": null,
            "putById": null,
            "respDef": null,
            "tag": "ContactAddress"
        }
    ]
}